pybahn/__init__.py
pybahn/_core.py
pybahn/version.py
pybahn/structs/__init__.py
pybahn/structs/_internal.py
pybahn/structs/travellers.py
pybahn-0.1.16.dist-info/licenses/LICENSE
pybahn-0.1.16.dist-info/METADATA
pybahn-0.1.16.dist-info/WHEEL
pybahn-0.1.16.dist-info/top_level.txt
pybahn-0.1.16.dist-info/RECORD
