Metadata-Version: 2.4
Name: PyBahn
Version: 0.1.16
Summary: A Python library for interacting with Deutsche Bahn data.
Author: qwwesq
Project-URL: Repository, https://github.com/qwwesq/PyBahn
Classifier: Programming Language :: Python :: 3
Classifier: Operating System :: OS Independent
Requires-Python: >=3.9
License-File: LICENSE
Requires-Dist: requests>=2.31.0
Requires-Dist: reportlab>=4.0.0
Dynamic: license-file
